fabpy/__init__.py
fabpy/absolute.py
fabpy/constants.py
fabpy/dataclass.py
fabpy/indirect.py
fabpy/utils.py
fabpy-1.1.3.dist-info/METADATA
fabpy-1.1.3.dist-info/WHEEL
fabpy-1.1.3.dist-info/top_level.txt
fabpy-1.1.3.dist-info/RECORD
