Metadata-Version: 2.2
Name: fabpy
Version: 1.1.3
Summary: Python library for calculating and formatting errors in LaTeX in lab work.
Home-page: https://github.com/SerKin0/fabpy
Author: SerKin0
Author-email: sergey.skor007@gmail.com
Requires-Python: >=3.6
Requires-Dist: numpy>=1.21.0
Requires-Dist: sympy>=1.9
Dynamic: author
Dynamic: author-email
Dynamic: description
Dynamic: description-content-type
Dynamic: home-page
Dynamic: requires-dist
Dynamic: requires-python
Dynamic: summary
